{"date-time": "13 May 2020, 08:00 IST (GMT+5:30)", "confirmed": 74281, "active": 47480, "recovered": 24385, "deceased": 2415, "migrated": 1, "state-wise": [{"name": "Andaman and Nicobar Islands", "confirmed": 33, "recovered": 33, "deceased": 0}, {"name": "Andhra Pradesh", "confirmed": 2090, "recovered": 1056, "deceased": 46}, {"name": "Arunachal Pradesh", "confirmed": 1, "recovered": 1, "deceased": 0}, {"name": "Assam", "confirmed": 65, "recovered": 39, "deceased": 2}, {"name": "Bihar", "confirmed": 831, "recovered": 383, "deceased": 6}, {"name": "Chandigarh", "confirmed": 187, "recovered": 28, "deceased": 3}, {"name": "Chhattisgarh", "confirmed": 59, "recovered": 54, "deceased": 0}, {"name": "Dadar Nagar Haveli", "confirmed": 1, "recovered": 0, "deceased": 0}, {"name": "Delhi", "confirmed": 7639, "recovered": 2512, "deceased": 86}, {"name": "Goa", "confirmed": 7, "recovered": 7, "deceased": 0}, {"name": "Gujarat", "confirmed": 8903, "recovered": 3246, "deceased": 537}, {"name": "Haryana", "confirmed": 780, "recovered": 342, "deceased": 11}, {"name": "Himachal Pradesh", "confirmed": 65, "recovered": 39, "deceased": 2}, {"name": "Jammu and Kashmir", "confirmed": 934, "recovered": 455, "deceased": 10}, {"name": "Jharkhand", "confirmed": 172, "recovered": 79, "deceased": 3}, {"name": "Karnataka", "confirmed": 925, "recovered": 433, "deceased": 31}, {"name": "Kerala", "confirmed": 524, "recovered": 489, "deceased": 4}, {"name": "Ladakh", "confirmed": 42, "recovered": 21, "deceased": 0}, {"name": "Madhya Pradesh", "confirmed": 3986, "recovered": 1860, "deceased": 225}, {"name": "Maharashtra", "confirmed": 24427, "recovered": 5125, "deceased": 921}, {"name": "Manipur", "confirmed": 2, "recovered": 2, "deceased": 0}, {"name": "Meghalaya", "confirmed": 13, "recovered": 10, "deceased": 1}, {"name": "Mizoram", "confirmed": 1, "recovered": 1, "deceased": 0}, {"name": "Odisha", "confirmed": 437, "recovered": 116, "deceased": 3}, {"name": "Puducherry", "confirmed": 13, "recovered": 9, "deceased": 1}, {"name": "Punjab", "confirmed": 1914, "recovered": 171, "deceased": 32}, {"name": "Rajasthan", "confirmed": 4126, "recovered": 2378, "deceased": 117}, {"name": "Tamil Nadu", "confirmed": 8718, "recovered": 2134, "deceased": 61}, {"name": "Telengana", "confirmed": 1326, "recovered": 830, "deceased": 32}, {"name": "Tripura", "confirmed": 154, "recovered": 2, "deceased": 0}, {"name": "Uttarakhand", "confirmed": 69, "recovered": 46, "deceased": 1}, {"name": "Uttar Pradesh", "confirmed": 3664, "recovered": 1873, "deceased": 82}, {"name": "West Bengal", "confirmed": 2173, "recovered": 612, "deceased": 198}]}